{

"bahmni_clinical_patients_search_TuberculosisReferralOrder": {
        "id": "bahmni.clinical.patients.search.TuberculosisReferralOrder",
        "extensionPointId": "org.bahmni.patient.search",
        "type": "config",
        "extensionParams": {
            "searchHandler": "emrapi.sqlSearch.active.TuberculosisReferralOrder",
            "display": "Department Of Tuberculosis",
            "forwardUrl": "../orders/#/patient/{{patientUuid}}/fulfillment/Department Of Tuberculosis",
            "forwardButtonTitle": "View",
            "view": "tabular"
        },
        "transitionKey": "Department Of Tuberculosis",
        "order": 1,
        "requiredPrivilege": "app:orders"
    }
}